README.rst
setup.py
deep_mapper/__init__.py
deep_mapper.egg-info/PKG-INFO
deep_mapper.egg-info/SOURCES.txt
deep_mapper.egg-info/dependency_links.txt
deep_mapper.egg-info/not-zip-safe
deep_mapper.egg-info/top_level.txt