Metadata-Version: 1.0
Name: deep-mapper
Version: 0.1.1
Summary: Mapper that able to return an object with converted keys, or a list of objects
Home-page: http://github.com/gebriallairbeg/deep_mapper
Author: Pavel Sherepo
Author-email: pavel.sherepo@gmail.com
License: MIT
Platform: UNKNOWN
